<?xml version="1.0" ?>
<tv date="20251129102436 +0800">
	<channel id="CCTV-1">
		<display-name lang="zh">CCTV-1</display-name>
	</channel>
	<programme channel="CCTV-1" start="20251129003900 +0800" stop="20251129010900 +0800">
		<title lang="zh">今日说法-2025-228</title>
	</programme>
	<programme channel="CCTV-1" start="20251129010900 +0800" stop="20251129014100 +0800">
		<title lang="zh">晚间新闻</title>
	</programme>
	<programme channel="CCTV-1" start="20251129014100 +0800" stop="20251129022800 +0800">
		<title lang="zh">开讲啦-2025-38</title>
	</programme>
	<programme channel="CCTV-1" start="20251129022800 +0800" stop="20251129023800 +0800">
		<title lang="zh">2024秘境之眼-秘境飞羽(4K)</title>
	</programme>
	<programme channel="CCTV-1" start="20251129023800 +0800" stop="20251129024700 +0800">
		<title lang="zh">三餐四季（第二季）-宣传片</title>
	</programme>
	<programme channel="CCTV-1" start="20251129024700 +0800" stop="20251129042000 +0800">
		<title lang="zh">山水间的家（第四季）-5</title>
	</programme>
	<programme channel="CCTV-1" start="20251129042000 +0800" stop="20251129042200 +0800">
		<title lang="zh">泱泱中华-历史文化街区1</title>
	</programme>
	<programme channel="CCTV-1" start="20251129042200 +0800" stop="20251129045300 +0800">
		<title lang="zh">今日说法-2025-228</title>
	</programme>
	<programme channel="CCTV-1" start="20251129045300 +0800" stop="20251129052700 +0800">
		<title lang="zh">新闻联播</title>
	</programme>
	<programme channel="CCTV-1" start="20251129052700 +0800" stop="20251129060000 +0800">
		<title lang="zh">寻古中国（第二季）-寻商记5</title>
	</programme>
	<programme channel="CCTV-1" start="20251129060000 +0800" stop="20251129083700 +0800">
		<title lang="zh">朝闻天下</title>
	</programme>
	<programme channel="CCTV-1" start="20251129083700 +0800" stop="20251129092300 +0800">
		<title lang="zh">生活早参考-特别节目（生活圈）2025-255</title>
	</programme>
	<programme channel="CCTV-1" start="20251129092300 +0800" stop="20251129101400 +0800">
		<title lang="zh">四喜第17集</title>
	</programme>
	<programme channel="CCTV-1" start="20251129101400 +0800" stop="20251129110600 +0800">
		<title lang="zh">四喜第18集</title>
	</programme>
	<programme channel="CCTV-1" start="20251129110600 +0800" stop="20251129115300 +0800">
		<title lang="zh">四喜第19集</title>
	</programme>
	<programme channel="CCTV-1" start="20251129115300 +0800" stop="20251129120000 +0800">
		<title lang="zh">秘境之眼-2025-323</title>
	</programme>
	<programme channel="CCTV-1" start="20251129120000 +0800" stop="20251129123500 +0800">
		<title lang="zh">新闻30分</title>
	</programme>
	<programme channel="CCTV-1" start="20251129123500 +0800" stop="20251129133600 +0800">
		<title lang="zh">踏歌行-7</title>
	</programme>
	<programme channel="CCTV-1" start="20251129133600 +0800" stop="20251129142600 +0800">
		<title lang="zh">隐锋第31集</title>
	</programme>
	<programme channel="CCTV-1" start="20251129142600 +0800" stop="20251129151500 +0800">
		<title lang="zh">隐锋第32集</title>
	</programme>
	<programme channel="CCTV-1" start="20251129151500 +0800" stop="20251129160400 +0800">
		<title lang="zh">隐锋第33集</title>
	</programme>
	<programme channel="CCTV-1" start="20251129160400 +0800" stop="20251129165700 +0800">
		<title lang="zh">隐锋第34集</title>
	</programme>
	<programme channel="CCTV-1" start="20251129165700 +0800" stop="20251129181900 +0800">
		<title lang="zh">星光大道-2025-50（这一站星光43）</title>
	</programme>
	<programme channel="CCTV-1" start="20251129181900 +0800" stop="20251129185000 +0800">
		<title lang="zh">寻味山海-漳州</title>
	</programme>
	<programme channel="CCTV-1" start="20251129185000 +0800" stop="20251129190000 +0800">
		<title lang="zh">秘境之眼-2025-330</title>
	</programme>
	<programme channel="CCTV-1" start="20251129190000 +0800" stop="20251129193900 +0800">
		<title lang="zh">新闻联播</title>
	</programme>
	<programme channel="CCTV-1" start="20251129193900 +0800" stop="20251129200600 +0800">
		<title lang="zh">焦点访谈</title>
	</programme>
	<programme channel="CCTV-1" start="20251129200600 +0800" stop="20251129214500 +0800">
		<title lang="zh">宗师列传·大宋词人传-李清照</title>
	</programme>
	<programme channel="CCTV-1" start="20251129214500 +0800" stop="20251129220000 +0800">
		<title lang="zh">山水间的家-主题曲</title>
	</programme>
	<programme channel="CCTV-1" start="20251129220000 +0800" stop="20251129223500 +0800">
		<title lang="zh">晚间新闻</title>
	</programme>
	<programme channel="CCTV-1" start="20251129223500 +0800" stop="20251129232400 +0800">
		<title lang="zh">开讲啦-2025-39</title>
	</programme>
	<programme channel="CCTV-1" start="20251129232400 +0800" stop="20251129235900 +0800">
		<title lang="zh">星光大道-2025-50（这一站星光43）</title>
	</programme>
	<channel id="CCTV-10">
		<display-name lang="zh">CCTV-10</display-name>
	</channel>
	<programme channel="CCTV-10" start="20251129000500 +0800" stop="20251129004500 +0800">
		<title lang="zh">读书-2025-382</title>
	</programme>
	<programme channel="CCTV-10" start="20251129004500 +0800" stop="20251129011500 +0800">
		<title lang="zh">透视新科技-2025-96</title>
	</programme>
	<programme channel="CCTV-10" start="20251129011500 +0800" stop="20251129014500 +0800">
		<title lang="zh">味道-2025-239（精编）</title>
	</programme>
	<programme channel="CCTV-10" start="20251129014500 +0800" stop="20251129022500 +0800">
		<title lang="zh">健康之路-2025-332</title>
	</programme>
	<programme channel="CCTV-10" start="20251129022500 +0800" stop="20251129030500 +0800">
		<title lang="zh">百家讲坛-2025-332</title>
	</programme>
	<programme channel="CCTV-10" start="20251129030500 +0800" stop="20251129060000 +0800">
		<title lang="zh">再见</title>
	</programme>
	<programme channel="CCTV-10" start="20251129060000 +0800" stop="20251129061000 +0800">
		<title lang="zh">读书-2025-333</title>
	</programme>
	<programme channel="CCTV-10" start="20251129061000 +0800" stop="20251129062000 +0800">
		<title lang="zh">百家说故事-2025-333</title>
	</programme>
	<programme channel="CCTV-10" start="20251129062000 +0800" stop="20251129063000 +0800">
		<title lang="zh">时尚科技秀-2025-333</title>
	</programme>
	<programme channel="CCTV-10" start="20251129063000 +0800" stop="20251129071300 +0800">
		<title lang="zh">健康之路-2025-332</title>
	</programme>
	<programme channel="CCTV-10" start="20251129071300 +0800" stop="20251129075700 +0800">
		<title lang="zh">科幻地带-2025-49</title>
	</programme>
	<programme channel="CCTV-10" start="20251129075700 +0800" stop="20251129080000 +0800">
		<title lang="zh">欣赏-2024年30秒-9</title>
	</programme>
	<programme channel="CCTV-10" start="20251129080000 +0800" stop="20251129084800 +0800">
		<title lang="zh">探索·发现-2025-332</title>
	</programme>
	<programme channel="CCTV-10" start="20251129084800 +0800" stop="20251129094500 +0800">
		<title lang="zh">2025科教纪录片精选-18</title>
	</programme>
	<programme channel="CCTV-10" start="20251129094500 +0800" stop="20251129102200 +0800">
		<title lang="zh">地理·中国-2025-332</title>
	</programme>
	<programme channel="CCTV-10" start="20251129102200 +0800" stop="20251129112200 +0800">
		<title lang="zh">自然传奇-2025-333</title>
	</programme>
	<programme channel="CCTV-10" start="20251129112200 +0800" stop="20251129120000 +0800">
		<title lang="zh">味道-2025-239（精编）</title>
	</programme>
	<programme channel="CCTV-10" start="20251129120000 +0800" stop="20251129124900 +0800">
		<title lang="zh">百家讲坛-2025-333</title>
	</programme>
	<programme channel="CCTV-10" start="20251129124900 +0800" stop="20251129135500 +0800">
		<title lang="zh">剧说历史（第一季）-69</title>
	</programme>
	<programme channel="CCTV-10" start="20251129135500 +0800" stop="20251129140000 +0800">
		<title lang="zh">欣赏-2024年30秒-9</title>
	</programme>
	<programme channel="CCTV-10" start="20251129140000 +0800" stop="20251129143500 +0800">
		<title lang="zh">地理·中国-2025-332</title>
	</programme>
	<programme channel="CCTV-10" start="20251129143500 +0800" stop="20251129153200 +0800">
		<title lang="zh">奥秘（精编）-5</title>
	</programme>
	<programme channel="CCTV-10" start="20251129153200 +0800" stop="20251129162700 +0800">
		<title lang="zh">奥秘（精编）-6</title>
	</programme>
	<programme channel="CCTV-10" start="20251129162700 +0800" stop="20251129172700 +0800">
		<title lang="zh">自然传奇-2025-333</title>
	</programme>
	<programme channel="CCTV-10" start="20251129172700 +0800" stop="20251129180500 +0800">
		<title lang="zh">地理·中国-2025-333</title>
	</programme>
	<programme channel="CCTV-10" start="20251129180500 +0800" stop="20251129185400 +0800">
		<title lang="zh">健康之路-2025-333</title>
	</programme>
	<programme channel="CCTV-10" start="20251129185400 +0800" stop="20251129193200 +0800">
		<title lang="zh">味道-2025-104</title>
	</programme>
	<programme channel="CCTV-10" start="20251129193200 +0800" stop="20251129203100 +0800">
		<title lang="zh">自然传奇-2025-334</title>
	</programme>
	<programme channel="CCTV-10" start="20251129203100 +0800" stop="20251129222300 +0800">
		<title lang="zh">中国水墨大会（第一季）-1</title>
	</programme>
	<programme channel="CCTV-10" start="20251129222300 +0800" stop="20251129231000 +0800">
		<title lang="zh">探索·发现-2025-333</title>
	</programme>
	<programme channel="CCTV-10" start="20251129231000 +0800" stop="20251129235900 +0800">
		<title lang="zh">考古公开课-2025-47</title>
	</programme>
	<channel id="CCTV-2">
		<display-name lang="zh">CCTV-2</display-name>
	</channel>
	<programme channel="CCTV-2" start="20251129002600 +0800" stop="20251129011800 +0800">
		<title lang="zh">乡村振兴中国行（第四季）-36</title>
	</programme>
	<programme channel="CCTV-2" start="20251129011800 +0800" stop="20251129020100 +0800">
		<title lang="zh">对话-2025-43</title>
	</programme>
	<programme channel="CCTV-2" start="20251129020100 +0800" stop="20251129025900 +0800">
		<title lang="zh">职场健康课-2025-47</title>
	</programme>
	<programme channel="CCTV-2" start="20251129025900 +0800" stop="20251129030700 +0800">
		<title lang="zh">周末特供2022-万物之生2-8分版</title>
	</programme>
	<programme channel="CCTV-2" start="20251129030700 +0800" stop="20251129033700 +0800">
		<title lang="zh">周末特供2025-大泰山6</title>
	</programme>
	<programme channel="CCTV-2" start="20251129033700 +0800" stop="20251129043500 +0800">
		<title lang="zh">一槌定音-2025-44</title>
	</programme>
	<programme channel="CCTV-2" start="20251129043500 +0800" stop="20251129050300 +0800">
		<title lang="zh">回家吃饭-2025-254</title>
	</programme>
	<programme channel="CCTV-2" start="20251129050300 +0800" stop="20251129053400 +0800">
		<title lang="zh">消费主张</title>
	</programme>
	<programme channel="CCTV-2" start="20251129053400 +0800" stop="20251129055900 +0800">
		<title lang="zh">生财有道-2025-11-28</title>
	</programme>
	<programme channel="CCTV-2" start="20251129055900 +0800" stop="20251129070000 +0800">
		<title lang="zh">经济信息联播</title>
	</programme>
	<programme channel="CCTV-2" start="20251129070000 +0800" stop="20251129090100 +0800">
		<title lang="zh">第一时间</title>
	</programme>
	<programme channel="CCTV-2" start="20251129090100 +0800" stop="20251129094000 +0800">
		<title lang="zh">周末特供2025-城市脉动2</title>
	</programme>
	<programme channel="CCTV-2" start="20251129094000 +0800" stop="20251129103100 +0800">
		<title lang="zh">周末特供2025-大地之上1</title>
	</programme>
	<programme channel="CCTV-2" start="20251129103100 +0800" stop="20251129104500 +0800">
		<title lang="zh">周末特供2025-945</title>
	</programme>
	<programme channel="CCTV-2" start="20251129104500 +0800" stop="20251129110000 +0800">
		<title lang="zh">周末特供2025-967</title>
	</programme>
	<programme channel="CCTV-2" start="20251129110000 +0800" stop="20251129110800 +0800">
		<title lang="zh">周末特供2023-乡野有真味1-8分版</title>
	</programme>
	<programme channel="CCTV-2" start="20251129110800 +0800" stop="20251129112800 +0800">
		<title lang="zh">2023精品财经纪-日出之食第四季-8</title>
	</programme>
	<programme channel="CCTV-2" start="20251129112800 +0800" stop="20251129120000 +0800">
		<title lang="zh">2022精品财经纪录-傲椒的湘菜第二季1</title>
	</programme>
	<programme channel="CCTV-2" start="20251129120000 +0800" stop="20251129130100 +0800">
		<title lang="zh">天下财经</title>
	</programme>
	<programme channel="CCTV-2" start="20251129130100 +0800" stop="20251129132500 +0800">
		<title lang="zh">周末特供2024-鲜生史第二季6</title>
	</programme>
	<programme channel="CCTV-2" start="20251129132500 +0800" stop="20251129135200 +0800">
		<title lang="zh">2022精品财经纪录-有面有朋友-3</title>
	</programme>
	<programme channel="CCTV-2" start="20251129135200 +0800" stop="20251129144400 +0800">
		<title lang="zh">乡村振兴中国行（第四季）-36</title>
	</programme>
	<programme channel="CCTV-2" start="20251129144400 +0800" stop="20251129154600 +0800">
		<title lang="zh">一槌定音-2025-49</title>
	</programme>
	<programme channel="CCTV-2" start="20251129154600 +0800" stop="20251129161200 +0800">
		<title lang="zh">2025精品财经纪录-青海我们的国家公园第二季-1</title>
	</programme>
	<programme channel="CCTV-2" start="20251129161200 +0800" stop="20251129163200 +0800">
		<title lang="zh">周末特供2025-1026</title>
	</programme>
	<programme channel="CCTV-2" start="20251129163200 +0800" stop="20251129165600 +0800">
		<title lang="zh">周末特供2025-1027</title>
	</programme>
	<programme channel="CCTV-2" start="20251129165600 +0800" stop="20251129172600 +0800">
		<title lang="zh">2022精品财经纪录-潮州味道-3</title>
	</programme>
	<programme channel="CCTV-2" start="20251129172600 +0800" stop="20251129175800 +0800">
		<title lang="zh">2022精品财经纪录-乡厨-3</title>
	</programme>
	<programme channel="CCTV-2" start="20251129175800 +0800" stop="20251129183000 +0800">
		<title lang="zh">2022精品财经纪录-乡厨-4</title>
	</programme>
	<programme channel="CCTV-2" start="20251129183000 +0800" stop="20251129193000 +0800">
		<title lang="zh">欢乐大猜想-2025-48</title>
	</programme>
	<programme channel="CCTV-2" start="20251129193000 +0800" stop="20251129203000 +0800">
		<title lang="zh">寻找国宝传颂人-2025中国国宝大会-3</title>
	</programme>
	<programme channel="CCTV-2" start="20251129203000 +0800" stop="20251129213000 +0800">
		<title lang="zh">经济信息联播</title>
	</programme>
	<programme channel="CCTV-2" start="20251129213000 +0800" stop="20251129221600 +0800">
		<title lang="zh">对话-2025-44</title>
	</programme>
	<programme channel="CCTV-2" start="20251129221600 +0800" stop="20251129224100 +0800">
		<title lang="zh">2023精品财经纪录-守望秦岭-1</title>
	</programme>
	<programme channel="CCTV-2" start="20251129224100 +0800" stop="20251129231000 +0800">
		<title lang="zh">2023精品财经纪录-守望秦岭-2</title>
	</programme>
	<programme channel="CCTV-2" start="20251129231000 +0800" stop="20251129235900 +0800">
		<title lang="zh">欢乐大猜想-2025-48</title>
	</programme>
	<channel id="CCTV-3">
		<display-name lang="zh">CCTV-3</display-name>
	</channel>
	<programme channel="CCTV-3" start="20251129000600 +0800" stop="20251129005200 +0800">
		<title lang="zh">综艺喜乐汇-2025-1321 青春之城 9/33</title>
	</programme>
	<programme channel="CCTV-3" start="20251129005200 +0800" stop="20251129013800 +0800">
		<title lang="zh">综艺喜乐汇-2025-1322 青春之城10/33</title>
	</programme>
	<programme channel="CCTV-3" start="20251129013800 +0800" stop="20251129032900 +0800">
		<title lang="zh">影视留声机-2025-90-经典电影欣赏《永不消逝的电波》</title>
	</programme>
	<programme channel="CCTV-3" start="20251129032900 +0800" stop="20251129050100 +0800">
		<title lang="zh">中央广播电视总台主持人大赛新闻主播季-12</title>
	</programme>
	<programme channel="CCTV-3" start="20251129050100 +0800" stop="20251129053100 +0800">
		<title lang="zh">衣锦天下丝路季-10</title>
	</programme>
	<programme channel="CCTV-3" start="20251129053100 +0800" stop="20251129053200 +0800">
		<title lang="zh">精彩艺瞬间-56</title>
	</programme>
	<programme channel="CCTV-3" start="20251129053200 +0800" stop="20251129063300 +0800">
		<title lang="zh">综艺盛典-2025-17选对健康17</title>
	</programme>
	<programme channel="CCTV-3" start="20251129063300 +0800" stop="20251129065400 +0800">
		<title lang="zh">文化十分-2025-244</title>
	</programme>
	<programme channel="CCTV-3" start="20251129065400 +0800" stop="20251129072500 +0800">
		<title lang="zh">慕名而来-5</title>
	</programme>
	<programme channel="CCTV-3" start="20251129072500 +0800" stop="20251129073200 +0800">
		<title lang="zh">国家宝藏-周游季-59</title>
	</programme>
	<programme channel="CCTV-3" start="20251129073200 +0800" stop="20251129083600 +0800">
		<title lang="zh">精彩音乐汇-我的爱对你说-2025-382</title>
	</programme>
	<programme channel="CCTV-3" start="20251129083600 +0800" stop="20251129084200 +0800">
		<title lang="zh">精彩艺瞬间-52</title>
	</programme>
	<programme channel="CCTV-3" start="20251129084200 +0800" stop="20251129115800 +0800">
		<title lang="zh">中国唱将-6</title>
	</programme>
	<programme channel="CCTV-3" start="20251129115800 +0800" stop="20251129132200 +0800">
		<title lang="zh">越战越勇-2025-34</title>
	</programme>
	<programme channel="CCTV-3" start="20251129132200 +0800" stop="20251129133300 +0800">
		<title lang="zh">国家宝藏-周游季-68</title>
	</programme>
	<programme channel="CCTV-3" start="20251129133300 +0800" stop="20251129150200 +0800">
		<title lang="zh">向幸福出发-2025-14</title>
	</programme>
	<programme channel="CCTV-3" start="20251129150200 +0800" stop="20251129151400 +0800">
		<title lang="zh">国家宝藏-周游季-57</title>
	</programme>
	<programme channel="CCTV-3" start="20251129151400 +0800" stop="20251129164500 +0800">
		<title lang="zh">星光大道-2025-34（这一站星光27）</title>
	</programme>
	<programme channel="CCTV-3" start="20251129164500 +0800" stop="20251129174200 +0800">
		<title lang="zh">绽放吧！妈妈-29</title>
	</programme>
	<programme channel="CCTV-3" start="20251129174200 +0800" stop="20251129175400 +0800">
		<title lang="zh">国家宝藏-周游季-58</title>
	</programme>
	<programme channel="CCTV-3" start="20251129175400 +0800" stop="20251129192100 +0800">
		<title lang="zh">开门大吉-2025-43</title>
	</programme>
	<programme channel="CCTV-3" start="20251129192100 +0800" stop="20251129193000 +0800">
		<title lang="zh">国家宝藏-周游季-69</title>
	</programme>
	<programme channel="CCTV-3" start="20251129193000 +0800" stop="20251129205700 +0800">
		<title lang="zh">越战越勇-2025-40</title>
	</programme>
	<programme channel="CCTV-3" start="20251129205700 +0800" stop="20251129222300 +0800">
		<title lang="zh">星光大道-2025-35（这一站星光28）</title>
	</programme>
	<programme channel="CCTV-3" start="20251129222300 +0800" stop="20251129225400 +0800">
		<title lang="zh">衣锦天下丝路季-9</title>
	</programme>
	<programme channel="CCTV-3" start="20251129225400 +0800" stop="20251129234000 +0800">
		<title lang="zh">综艺喜乐汇-2025-1323 青春之城11/33</title>
	</programme>
	<programme channel="CCTV-3" start="20251129234000 +0800" stop="20251129235900 +0800">
		<title lang="zh">综艺喜乐汇-2025-1324 青春之城12/33</title>
	</programme>
	<channel id="CCTV-4">
		<display-name lang="zh">CCTV-4</display-name>
	</channel>
	<programme channel="CCTV-4" start="20251129003500 +0800" stop="20251129012100 +0800">
		<title lang="zh">火红年华第6集</title>
	</programme>
	<programme channel="CCTV-4" start="20251129012100 +0800" stop="20251129015000 +0800">
		<title lang="zh">国家记忆-2025-140</title>
	</programme>
	<programme channel="CCTV-4" start="20251129015000 +0800" stop="20251129020000 +0800">
		<title lang="zh">记住乡愁-片段展播-2025-10</title>
	</programme>
	<programme channel="CCTV-4" start="20251129020000 +0800" stop="20251129023000 +0800">
		<title lang="zh">新闻联播</title>
	</programme>
	<programme channel="CCTV-4" start="20251129023000 +0800" stop="20251129030000 +0800">
		<title lang="zh">鲁健访谈-2025-48</title>
	</programme>
	<programme channel="CCTV-4" start="20251129030000 +0800" stop="20251129031000 +0800">
		<title lang="zh">中国新闻</title>
	</programme>
	<programme channel="CCTV-4" start="20251129031000 +0800" stop="20251129040000 +0800">
		<title lang="zh">远方的家2025-112</title>
	</programme>
	<programme channel="CCTV-4" start="20251129040000 +0800" stop="20251129043000 +0800">
		<title lang="zh">中国新闻</title>
	</programme>
	<programme channel="CCTV-4" start="20251129043000 +0800" stop="20251129050000 +0800">
		<title lang="zh">今日关注</title>
	</programme>
	<programme channel="CCTV-4" start="20251129050000 +0800" stop="20251129053000 +0800">
		<title lang="zh">国家记忆-2025-177</title>
	</programme>
	<programme channel="CCTV-4" start="20251129053000 +0800" stop="20251129060000 +0800">
		<title lang="zh">鲁健访谈-2025-48</title>
	</programme>
	<programme channel="CCTV-4" start="20251129060000 +0800" stop="20251129063000 +0800">
		<title lang="zh">海峡两岸-2025-332</title>
	</programme>
	<programme channel="CCTV-4" start="20251129063000 +0800" stop="20251129070000 +0800">
		<title lang="zh">今日亚洲</title>
	</programme>
	<programme channel="CCTV-4" start="20251129070000 +0800" stop="20251129073000 +0800">
		<title lang="zh">中国新闻</title>
	</programme>
	<programme channel="CCTV-4" start="20251129073000 +0800" stop="20251129080000 +0800">
		<title lang="zh">今日关注</title>
	</programme>
	<programme channel="CCTV-4" start="20251129080000 +0800" stop="20251129090000 +0800">
		<title lang="zh">今日环球</title>
	</programme>
	<programme channel="CCTV-4" start="20251129090000 +0800" stop="20251129092700 +0800">
		<title lang="zh">今日亚洲</title>
	</programme>
	<programme channel="CCTV-4" start="20251129092700 +0800" stop="20251129095800 +0800">
		<title lang="zh">国家记忆-2025-166</title>
	</programme>
	<programme channel="CCTV-4" start="20251129095800 +0800" stop="20251129102500 +0800">
		<title lang="zh">国家记忆-2025-168</title>
	</programme>
	<programme channel="CCTV-4" start="20251129102500 +0800" stop="20251129105500 +0800">
		<title lang="zh">国家记忆-2025-169</title>
	</programme>
	<programme channel="CCTV-4" start="20251129105500 +0800" stop="20251129112600 +0800">
		<title lang="zh">国家记忆-2025-170</title>
	</programme>
	<programme channel="CCTV-4" start="20251129112600 +0800" stop="20251129120000 +0800">
		<title lang="zh">海峡两岸-2025-332</title>
	</programme>
	<programme channel="CCTV-4" start="20251129120000 +0800" stop="20251129130000 +0800">
		<title lang="zh">中国新闻</title>
	</programme>
	<programme channel="CCTV-4" start="20251129130000 +0800" stop="20251129132900 +0800">
		<title lang="zh">华人故事-2025-49</title>
	</programme>
	<programme channel="CCTV-4" start="20251129132900 +0800" stop="20251129141500 +0800">
		<title lang="zh">特赦1959第37集</title>
	</programme>
	<programme channel="CCTV-4" start="20251129141500 +0800" stop="20251129150100 +0800">
		<title lang="zh">特赦1959第38集</title>
	</programme>
	<programme channel="CCTV-4" start="20251129150100 +0800" stop="20251129154800 +0800">
		<title lang="zh">特赦1959第39集</title>
	</programme>
	<programme channel="CCTV-4" start="20251129154800 +0800" stop="20251129163500 +0800">
		<title lang="zh">战天狼第1集</title>
	</programme>
	<programme channel="CCTV-4" start="20251129163500 +0800" stop="20251129170100 +0800">
		<title lang="zh">中国缘-2025-47</title>
	</programme>
	<programme channel="CCTV-4" start="20251129170100 +0800" stop="20251129172800 +0800">
		<title lang="zh">百城头牌菜（第二季）-8</title>
	</programme>
	<programme channel="CCTV-4" start="20251129172800 +0800" stop="20251129174300 +0800">
		<title lang="zh">平凡匠心-2025-95</title>
	</programme>
	<programme channel="CCTV-4" start="20251129174300 +0800" stop="20251129180300 +0800">
		<title lang="zh">平凡匠心-2025-96</title>
	</programme>
	<programme channel="CCTV-4" start="20251129180300 +0800" stop="20251129183000 +0800">
		<title lang="zh">国家记忆-2025-141</title>
	</programme>
	<programme channel="CCTV-4" start="20251129183000 +0800" stop="20251129190000 +0800">
		<title lang="zh">国家记忆-2025-143</title>
	</programme>
	<programme channel="CCTV-4" start="20251129190000 +0800" stop="20251129194400 +0800">
		<title lang="zh">中国新闻</title>
	</programme>
	<programme channel="CCTV-4" start="20251129194400 +0800" stop="20251129203000 +0800">
		<title lang="zh">礼仪中国-1（四套重播）</title>
	</programme>
	<programme channel="CCTV-4" start="20251129203000 +0800" stop="20251129210000 +0800">
		<title lang="zh">海峡两岸-2025-333</title>
	</programme>
	<programme channel="CCTV-4" start="20251129210000 +0800" stop="20251129213000 +0800">
		<title lang="zh">中国新闻</title>
	</programme>
	<programme channel="CCTV-4" start="20251129213000 +0800" stop="20251129220000 +0800">
		<title lang="zh">今日关注</title>
	</programme>
	<programme channel="CCTV-4" start="20251129220000 +0800" stop="20251129223000 +0800">
		<title lang="zh">深度国际-2025年11月-5</title>
	</programme>
	<programme channel="CCTV-4" start="20251129223000 +0800" stop="20251129230200 +0800">
		<title lang="zh">新闻联播</title>
	</programme>
	<programme channel="CCTV-4" start="20251129230200 +0800" stop="20251129235900 +0800">
		<title lang="zh">健康中国-2025-47</title>
	</programme>
	<channel id="CCTV-5">
		<display-name lang="zh">CCTV-5</display-name>
	</channel>
	<programme channel="CCTV-5" start="20251129010500 +0800" stop="20251129023600 +0800">
		<title lang="zh">实况录像-2025年中国羽毛球大师赛 1</title>
	</programme>
	<programme channel="CCTV-5" start="20251129023600 +0800" stop="20251129040000 +0800">
		<title lang="zh">实况录像-2024/2025赛季中国男子篮球职业联赛 季后赛 总决赛 4</title>
	</programme>
	<programme channel="CCTV-5" start="20251129040000 +0800" stop="20251129053000 +0800">
		<title lang="zh">国际足球赛场-25-26赛季英超联赛第5轮 布赖顿—托特纳姆</title>
	</programme>
	<programme channel="CCTV-5" start="20251129053000 +0800" stop="20251129060000 +0800">
		<title lang="zh">实况录像-2025年射箭世界杯 西班牙站 1</title>
	</programme>
	<programme channel="CCTV-5" start="20251129060000 +0800" stop="20251129063000 +0800">
		<title lang="zh">实况录像-2025年三人篮球世界杯 6</title>
	</programme>
	<programme channel="CCTV-5" start="20251129063000 +0800" stop="20251129070000 +0800">
		<title lang="zh">健身动起来</title>
	</programme>
	<programme channel="CCTV-5" start="20251129070000 +0800" stop="20251129083000 +0800">
		<title lang="zh">体坛晨报</title>
	</programme>
	<programme channel="CCTV-5" start="20251129083000 +0800" stop="20251129110000 +0800">
		<title lang="zh">2025/2026赛季美国职业篮球联赛-杯赛小组赛（雄鹿-尼克斯）</title>
	</programme>
	<programme channel="CCTV-5" start="20251129110000 +0800" stop="20251129120000 +0800">
		<title lang="zh">实况录像（奥林匹克）-第十五届全国运动会 田径比赛2（4K）</title>
	</programme>
	<programme channel="CCTV-5" start="20251129120000 +0800" stop="20251129123000 +0800">
		<title lang="zh">体坛快讯</title>
	</programme>
	<programme channel="CCTV-5" start="20251129123000 +0800" stop="20251129141000 +0800">
		<title lang="zh">2025/2026赛季国际雪联大跳台世界杯（云顶站）-单板滑雪 女子、男子决赛</title>
	</programme>
	<programme channel="CCTV-5" start="20251129141000 +0800" stop="20251129150500 +0800">
		<title lang="zh">实况录像（奥林匹克）-第十五届全国运动会 跳水女子3米板决赛（4K）</title>
	</programme>
	<programme channel="CCTV-5" start="20251129150500 +0800" stop="20251129163000 +0800">
		<title lang="zh">实况录像-2025/2026赛季欧洲篮球联赛 第13轮 摩纳哥—伊斯坦布尔</title>
	</programme>
	<programme channel="CCTV-5" start="20251129163000 +0800" stop="20251129180000 +0800">
		<title lang="zh">实况录像（奥林匹克）-第十五届全国运动会 排球女子决赛（4K）</title>
	</programme>
	<programme channel="CCTV-5" start="20251129180000 +0800" stop="20251129190500 +0800">
		<title lang="zh">体育新闻</title>
	</programme>
	<programme channel="CCTV-5" start="20251129190500 +0800" stop="20251129193500 +0800">
		<title lang="zh">2025/2026西班牙足球甲级联赛-第13轮集锦</title>
	</programme>
	<programme channel="CCTV-5" start="20251129193500 +0800" stop="20251129203500 +0800">
		<title lang="zh">实况录像（奥林匹克）-全运全记录 8（4K）</title>
	</programme>
	<programme channel="CCTV-5" start="20251129203500 +0800" stop="20251129210000 +0800">
		<title lang="zh">2025/2026赛季雪车世界杯 意大利科尔蒂纳站-男子钢架雪车</title>
	</programme>
	<programme channel="CCTV-5" start="20251129210000 +0800" stop="20251129230000 +0800">
		<title lang="zh">2025/2026赛季斯诺克英国锦标赛- 第1轮</title>
	</programme>
	<programme channel="CCTV-5" start="20251129230000 +0800" stop="20251129235900 +0800">
		<title lang="zh">2025/2026英格兰足球超级联赛-第13轮（曼城—利兹联）</title>
	</programme>
	<channel id="CCTV-5+">
		<display-name lang="zh">CCTV-5+</display-name>
	</channel>
	<programme channel="CCTV-5+" start="20251129001000 +0800" stop="20251129011100 +0800">
		<title lang="zh">实况录像（奥林匹克）-第十五届全国运动会 羽毛球男单决赛（4K）</title>
	</programme>
	<programme channel="CCTV-5+" start="20251129011100 +0800" stop="20251129023800 +0800">
		<title lang="zh">实况录像-2024/2025赛季中国男子篮球职业联赛 季后赛 半决赛 2</title>
	</programme>
	<programme channel="CCTV-5+" start="20251129023800 +0800" stop="20251129040000 +0800">
		<title lang="zh">国际足球赛场-25-26赛季英超联赛第6轮 阿斯顿维拉—富勒姆</title>
	</programme>
	<programme channel="CCTV-5+" start="20251129040000 +0800" stop="20251129060000 +0800">
		<title lang="zh">实况录像-2024/2025赛季世界斯诺克锦标赛 2</title>
	</programme>
	<programme channel="CCTV-5+" start="20251129060000 +0800" stop="20251129073000 +0800">
		<title lang="zh">实况录像-2025年世界田联钻石联赛  斯德哥尔摩站</title>
	</programme>
	<programme channel="CCTV-5+" start="20251129073000 +0800" stop="20251129090000 +0800">
		<title lang="zh">实况录像-2025年世界羽毛球锦标赛  1</title>
	</programme>
	<programme channel="CCTV-5+" start="20251129090000 +0800" stop="20251129103500 +0800">
		<title lang="zh">2025/2026赛季国际雪联大跳台世界杯（云顶站）-自由式滑雪 女子、男子决赛</title>
	</programme>
	<programme channel="CCTV-5+" start="20251129103500 +0800" stop="20251129120500 +0800">
		<title lang="zh">实况录像（奥林匹克）-第十五届全国运动会 羽毛球女子团体决赛</title>
	</programme>
	<programme channel="CCTV-5+" start="20251129120500 +0800" stop="20251129130500 +0800">
		<title lang="zh">实况录像（奥林匹克）-全运全记录 6（4K）</title>
	</programme>
	<programme channel="CCTV-5+" start="20251129130500 +0800" stop="20251129143500 +0800">
		<title lang="zh">实况录像-2025年WTT大满贯赛 中国站 1</title>
	</programme>
	<programme channel="CCTV-5+" start="20251129143500 +0800" stop="20251129160500 +0800">
		<title lang="zh">国际足球赛场-25-26赛季英超联赛第12轮 利兹联—阿斯顿维拉</title>
	</programme>
	<programme channel="CCTV-5+" start="20251129160500 +0800" stop="20251129170000 +0800">
		<title lang="zh">实况录像-2025年世界职业拳王争霸赛 16</title>
	</programme>
	<programme channel="CCTV-5+" start="20251129170000 +0800" stop="20251129173000 +0800">
		<title lang="zh">2025/2026赛季雪车世界杯 意大利科尔蒂纳站-男子钢架雪车</title>
	</programme>
	<programme channel="CCTV-5+" start="20251129173000 +0800" stop="20251129183000 +0800">
		<title lang="zh">实况录像（奥林匹克）-第十五届全国运动会 跳水男子3米板决赛（4K）</title>
	</programme>
	<programme channel="CCTV-5+" start="20251129183000 +0800" stop="20251129200000 +0800">
		<title lang="zh">实况录像（奥林匹克）-第十五届全国运动会 排球女子决赛（4K）</title>
	</programme>
	<programme channel="CCTV-5+" start="20251129200000 +0800" stop="20251129210000 +0800">
		<title lang="zh">实况录像-2025/2026赛季速度滑冰世界杯 加拿大站 2</title>
	</programme>
	<programme channel="CCTV-5+" start="20251129210000 +0800" stop="20251129214500 +0800">
		<title lang="zh">实况录像（奥林匹克）-第十五届全国运动会 跳水女子3米板决赛</title>
	</programme>
	<programme channel="CCTV-5+" start="20251129214500 +0800" stop="20251129231000 +0800">
		<title lang="zh">实况录像（奥林匹克）-第十五届全国运动会 体操男子团体决赛</title>
	</programme>
	<programme channel="CCTV-5+" start="20251129231000 +0800" stop="20251129235900 +0800">
		<title lang="zh">2025/2026西班牙足球甲级联赛-第14轮（巴塞罗那—阿拉维斯）</title>
	</programme>
	<channel id="CCTV-6">
		<display-name lang="zh">CCTV-6</display-name>
	</channel>
	<programme channel="CCTV-6" start="20251129000400 +0800" stop="20251129001700 +0800">
		<title lang="zh">今日影评2025-238</title>
	</programme>
	<programme channel="CCTV-6" start="20251129001700 +0800" stop="20251129015000 +0800">
		<title lang="zh">U57次谜案</title>
	</programme>
	<programme channel="CCTV-6" start="20251129015000 +0800" stop="20251129032100 +0800">
		<title lang="zh">相见在鸾峰桥</title>
	</programme>
	<programme channel="CCTV-6" start="20251129032100 +0800" stop="20251129062300 +0800">
		<title lang="zh">生活秀</title>
	</programme>
	<programme channel="CCTV-6" start="20251129062300 +0800" stop="20251129080000 +0800">
		<title lang="zh">六指琴魔</title>
	</programme>
	<programme channel="CCTV-6" start="20251129080000 +0800" stop="20251129095200 +0800">
		<title lang="zh">神州第一刀</title>
	</programme>
	<programme channel="CCTV-6" start="20251129095200 +0800" stop="20251129112700 +0800">
		<title lang="zh">木乃伊历险记</title>
	</programme>
	<programme channel="CCTV-6" start="20251129112700 +0800" stop="20251129113300 +0800">
		<title lang="zh">音乐电影欣赏</title>
	</programme>
	<programme channel="CCTV-6" start="20251129113300 +0800" stop="20251129130900 +0800">
		<title lang="zh">夜袭</title>
	</programme>
	<programme channel="CCTV-6" start="20251129130900 +0800" stop="20251129133200 +0800">
		<title lang="zh">《1905影视频》2025-048</title>
	</programme>
	<programme channel="CCTV-6" start="20251129133200 +0800" stop="20251129154700 +0800">
		<title lang="zh">刺杀小说家</title>
	</programme>
	<programme channel="CCTV-6" start="20251129154700 +0800" stop="20251129180200 +0800">
		<title lang="zh">悬崖之上</title>
	</programme>
	<programme channel="CCTV-6" start="20251129180200 +0800" stop="20251129194300 +0800">
		<title lang="zh">决战狂沙镇</title>
	</programme>
	<programme channel="CCTV-6" start="20251129194300 +0800" stop="20251129220000 +0800">
		<title lang="zh">九龙城寨之围城</title>
	</programme>
	<programme channel="CCTV-6" start="20251129220000 +0800" stop="20251129221800 +0800">
		<title lang="zh">中国电影报道 2025-333</title>
	</programme>
	<programme channel="CCTV-6" start="20251129221800 +0800" stop="20251129222300 +0800">
		<title lang="zh">中国福利彩票阳光开奖2025-11-29</title>
	</programme>
	<programme channel="CCTV-6" start="20251129222300 +0800" stop="20251129223200 +0800">
		<title lang="zh">佳片有约周六版2025-048</title>
	</programme>
	<programme channel="CCTV-6" start="20251129223200 +0800" stop="20251129230000 +0800">
		<title lang="zh">火海凌云（上）</title>
	</programme>
	<programme channel="CCTV-6" start="20251129230000 +0800" stop="20251129230100 +0800">
		<title lang="zh">中国体育彩票阳光开奖2025-11-29</title>
	</programme>
	<programme channel="CCTV-6" start="20251129230100 +0800" stop="20251129235900 +0800">
		<title lang="zh">火海凌云（下）</title>
	</programme>
	<channel id="CCTV-7">
		<display-name lang="zh">CCTV-7</display-name>
	</channel>
	<programme channel="CCTV-7" start="20251129000800 +0800" stop="20251129004600 +0800">
		<title lang="zh">兵器面面观-2025-238</title>
	</programme>
	<programme channel="CCTV-7" start="20251129004600 +0800" stop="20251129060300 +0800">
		<title lang="zh">再见</title>
	</programme>
	<programme channel="CCTV-7" start="20251129060300 +0800" stop="20251129063300 +0800">
		<title lang="zh">军事纪实-2025-238</title>
	</programme>
	<programme channel="CCTV-7" start="20251129063300 +0800" stop="20251129070400 +0800">
		<title lang="zh">砺剑-2025-48</title>
	</programme>
	<programme channel="CCTV-7" start="20251129070400 +0800" stop="20251129073000 +0800">
		<title lang="zh">国防故事-2025-204</title>
	</programme>
	<programme channel="CCTV-7" start="20251129073000 +0800" stop="20251129075800 +0800">
		<title lang="zh">国防军事早报</title>
	</programme>
	<programme channel="CCTV-7" start="20251129075800 +0800" stop="20251129090300 +0800">
		<title lang="zh">讲武堂-2025-47</title>
	</programme>
	<programme channel="CCTV-7" start="20251129090300 +0800" stop="20251129093500 +0800">
		<title lang="zh">防务新观察-2025-332</title>
	</programme>
	<programme channel="CCTV-7" start="20251129093500 +0800" stop="20251129100500 +0800">
		<title lang="zh">军事纪实-2025-238</title>
	</programme>
	<programme channel="CCTV-7" start="20251129100500 +0800" stop="20251129101700 +0800">
		<title lang="zh">国防微视频-军歌嘹亮-风吹沙（战旗版）</title>
	</programme>
	<programme channel="CCTV-7" start="20251129101700 +0800" stop="20251129120000 +0800">
		<title lang="zh">五星剧场-冰山上的来客</title>
	</programme>
	<programme channel="CCTV-7" start="20251129120000 +0800" stop="20251129123600 +0800">
		<title lang="zh">正午国防军事</title>
	</programme>
	<programme channel="CCTV-7" start="20251129123600 +0800" stop="20251129131000 +0800">
		<title lang="zh">防务新观察-2025-332</title>
	</programme>
	<programme channel="CCTV-7" start="20251129131000 +0800" stop="20251129134400 +0800">
		<title lang="zh">军武零距离-2025-47(4K)</title>
	</programme>
	<programme channel="CCTV-7" start="20251129134400 +0800" stop="20251129141400 +0800">
		<title lang="zh">军迷行天下-2025-48</title>
	</programme>
	<programme channel="CCTV-7" start="20251129141400 +0800" stop="20251129142000 +0800">
		<title lang="zh">国防微视频-军歌嘹亮-陆战雄风</title>
	</programme>
	<programme channel="CCTV-7" start="20251129142000 +0800" stop="20251129151100 +0800">
		<title lang="zh">掩不住的阳光14/38</title>
	</programme>
	<programme channel="CCTV-7" start="20251129151100 +0800" stop="20251129160000 +0800">
		<title lang="zh">掩不住的阳光15/38</title>
	</programme>
	<programme channel="CCTV-7" start="20251129160000 +0800" stop="20251129165100 +0800">
		<title lang="zh">掩不住的阳光16/38</title>
	</programme>
	<programme channel="CCTV-7" start="20251129165100 +0800" stop="20251129172100 +0800">
		<title lang="zh">军事科技-2025-47</title>
	</programme>
	<programme channel="CCTV-7" start="20251129172100 +0800" stop="20251129175100 +0800">
		<title lang="zh">第二战场-2025-48</title>
	</programme>
	<programme channel="CCTV-7" start="20251129175100 +0800" stop="20251129175700 +0800">
		<title lang="zh">国防微视频-军歌嘹亮-风吹沙（战旗版）</title>
	</programme>
	<programme channel="CCTV-7" start="20251129175700 +0800" stop="20251129182800 +0800">
		<title lang="zh">砺剑-2025-48</title>
	</programme>
	<programme channel="CCTV-7" start="20251129182800 +0800" stop="20251129190000 +0800">
		<title lang="zh">军营的味道-2025-48</title>
	</programme>
	<programme channel="CCTV-7" start="20251129190000 +0800" stop="20251129193300 +0800">
		<title lang="zh">新闻联播</title>
	</programme>
	<programme channel="CCTV-7" start="20251129193300 +0800" stop="20251129200300 +0800">
		<title lang="zh">军事报道</title>
	</programme>
	<programme channel="CCTV-7" start="20251129200300 +0800" stop="20251129200900 +0800">
		<title lang="zh">国防微视频-军歌嘹亮-陆战雄风</title>
	</programme>
	<programme channel="CCTV-7" start="20251129200900 +0800" stop="20251129204400 +0800">
		<title lang="zh">防务新观察-2025-333</title>
	</programme>
	<programme channel="CCTV-7" start="20251129204400 +0800" stop="20251129215200 +0800">
		<title lang="zh">老兵你好-2025-48</title>
	</programme>
	<programme channel="CCTV-7" start="20251129215200 +0800" stop="20251129224200 +0800">
		<title lang="zh">扫黑风暴16/28</title>
	</programme>
	<programme channel="CCTV-7" start="20251129224200 +0800" stop="20251129233700 +0800">
		<title lang="zh">扫黑风暴17/28</title>
	</programme>
	<programme channel="CCTV-7" start="20251129233700 +0800" stop="20251129235900 +0800">
		<title lang="zh">第二战场-2025-48</title>
	</programme>
	<channel id="CCTV-8">
		<display-name lang="zh">CCTV-8</display-name>
	</channel>
	<programme channel="CCTV-8" start="20251129000200 +0800" stop="20251129004800 +0800">
		<title lang="zh">我的后半生第5集</title>
	</programme>
	<programme channel="CCTV-8" start="20251129004800 +0800" stop="20251129013400 +0800">
		<title lang="zh">我的后半生第6集</title>
	</programme>
	<programme channel="CCTV-8" start="20251129013400 +0800" stop="20251129022000 +0800">
		<title lang="zh">我的后半生第7集</title>
	</programme>
	<programme channel="CCTV-8" start="20251129022000 +0800" stop="20251129030600 +0800">
		<title lang="zh">我的后半生第8集</title>
	</programme>
	<programme channel="CCTV-8" start="20251129030600 +0800" stop="20251129035200 +0800">
		<title lang="zh">我的后半生第9集</title>
	</programme>
	<programme channel="CCTV-8" start="20251129035200 +0800" stop="20251129043800 +0800">
		<title lang="zh">我的后半生第10集</title>
	</programme>
	<programme channel="CCTV-8" start="20251129043800 +0800" stop="20251129044200 +0800">
		<title lang="zh">插花-2022-3</title>
	</programme>
	<programme channel="CCTV-8" start="20251129044200 +0800" stop="20251129052800 +0800">
		<title lang="zh">刘家媳妇第37集</title>
	</programme>
	<programme channel="CCTV-8" start="20251129052800 +0800" stop="20251129061400 +0800">
		<title lang="zh">刘家媳妇第38集</title>
	</programme>
	<programme channel="CCTV-8" start="20251129061400 +0800" stop="20251129070400 +0800">
		<title lang="zh">刘家媳妇第39集</title>
	</programme>
	<programme channel="CCTV-8" start="20251129070400 +0800" stop="20251129075000 +0800">
		<title lang="zh">有你才有家第1集</title>
	</programme>
	<programme channel="CCTV-8" start="20251129075000 +0800" stop="20251129075800 +0800">
		<title lang="zh">星推荐-2025年11月-28</title>
	</programme>
	<programme channel="CCTV-8" start="20251129075800 +0800" stop="20251129085200 +0800">
		<title lang="zh">阵地第12集</title>
	</programme>
	<programme channel="CCTV-8" start="20251129085200 +0800" stop="20251129094200 +0800">
		<title lang="zh">阵地第13集</title>
	</programme>
	<programme channel="CCTV-8" start="20251129094200 +0800" stop="20251129095200 +0800">
		<title lang="zh">星推荐-2025年11月-28</title>
	</programme>
	<programme channel="CCTV-8" start="20251129095200 +0800" stop="20251129104800 +0800">
		<title lang="zh">阵地第14集</title>
	</programme>
	<programme channel="CCTV-8" start="20251129104800 +0800" stop="20251129114400 +0800">
		<title lang="zh">阵地第15集</title>
	</programme>
	<programme channel="CCTV-8" start="20251129114400 +0800" stop="20251129123000 +0800">
		<title lang="zh">阵地第16集</title>
	</programme>
	<programme channel="CCTV-8" start="20251129123000 +0800" stop="20251129124400 +0800">
		<title lang="zh">星推荐-2025年11月-28</title>
	</programme>
	<programme channel="CCTV-8" start="20251129124400 +0800" stop="20251129133900 +0800">
		<title lang="zh">狂飙第36集</title>
	</programme>
	<programme channel="CCTV-8" start="20251129133900 +0800" stop="20251129143400 +0800">
		<title lang="zh">狂飙第37集</title>
	</programme>
	<programme channel="CCTV-8" start="20251129143400 +0800" stop="20251129153100 +0800">
		<title lang="zh">狂飙第38集</title>
	</programme>
	<programme channel="CCTV-8" start="20251129153100 +0800" stop="20251129162600 +0800">
		<title lang="zh">狂飙第39集</title>
	</programme>
	<programme channel="CCTV-8" start="20251129162600 +0800" stop="20251129162900 +0800">
		<title lang="zh">插花-2015-3</title>
	</programme>
	<programme channel="CCTV-8" start="20251129162900 +0800" stop="20251129173100 +0800">
		<title lang="zh">生万物第26集</title>
	</programme>
	<programme channel="CCTV-8" start="20251129173100 +0800" stop="20251129182600 +0800">
		<title lang="zh">生万物第27集</title>
	</programme>
	<programme channel="CCTV-8" start="20251129182600 +0800" stop="20251129183300 +0800">
		<title lang="zh">星推荐-2025年11月-28</title>
	</programme>
	<programme channel="CCTV-8" start="20251129183300 +0800" stop="20251129192200 +0800">
		<title lang="zh">生万物第28集</title>
	</programme>
	<programme channel="CCTV-8" start="20251129192200 +0800" stop="20251129192700 +0800">
		<title lang="zh">星推荐-2025年11月-29</title>
	</programme>
	<programme channel="CCTV-8" start="20251129192700 +0800" stop="20251129193000 +0800">
		<title lang="zh">本集提要-大生意人-第9集</title>
	</programme>
	<programme channel="CCTV-8" start="20251129193000 +0800" stop="20251129202500 +0800">
		<title lang="zh">大生意人第9集</title>
	</programme>
	<programme channel="CCTV-8" start="20251129202500 +0800" stop="20251129203000 +0800">
		<title lang="zh">本集提要-大生意人-第10集</title>
	</programme>
	<programme channel="CCTV-8" start="20251129203000 +0800" stop="20251129212200 +0800">
		<title lang="zh">大生意人第10集</title>
	</programme>
	<programme channel="CCTV-8" start="20251129212200 +0800" stop="20251129212700 +0800">
		<title lang="zh">本集提要-即刻上场-第1集</title>
	</programme>
	<programme channel="CCTV-8" start="20251129212700 +0800" stop="20251129221600 +0800">
		<title lang="zh">即刻上场第1集</title>
	</programme>
	<programme channel="CCTV-8" start="20251129221600 +0800" stop="20251129221900 +0800">
		<title lang="zh">本集提要-即刻上场-第2集</title>
	</programme>
	<programme channel="CCTV-8" start="20251129221900 +0800" stop="20251129230800 +0800">
		<title lang="zh">即刻上场第2集</title>
	</programme>
	<programme channel="CCTV-8" start="20251129230800 +0800" stop="20251129235400 +0800">
		<title lang="zh">我的后半生第11集</title>
	</programme>
	<programme channel="CCTV-8" start="20251129235400 +0800" stop="20251129235900 +0800">
		<title lang="zh">星推荐-2025年11月-29</title>
	</programme>
	<channel id="CCTV-9">
		<display-name lang="zh">CCTV-9</display-name>
	</channel>
	<programme channel="CCTV-9" start="20251129003100 +0800" stop="20251129012700 +0800">
		<title lang="zh">全景自然2025-332</title>
	</programme>
	<programme channel="CCTV-9" start="20251129012700 +0800" stop="20251129022300 +0800">
		<title lang="zh">魅力万象2025-333</title>
	</programme>
	<programme channel="CCTV-9" start="20251129022300 +0800" stop="20251129025300 +0800">
		<title lang="zh">活力·源2025-349</title>
	</programme>
	<programme channel="CCTV-9" start="20251129025300 +0800" stop="20251129035400 +0800">
		<title lang="zh">特别呈现2025-327</title>
	</programme>
	<programme channel="CCTV-9" start="20251129035400 +0800" stop="20251129041100 +0800">
		<title lang="zh">9视频2025-332</title>
	</programme>
	<programme channel="CCTV-9" start="20251129041100 +0800" stop="20251129044600 +0800">
		<title lang="zh">活力·源2025-349</title>
	</programme>
	<programme channel="CCTV-9" start="20251129044600 +0800" stop="20251129054600 +0800">
		<title lang="zh">故事中国2025-309</title>
	</programme>
	<programme channel="CCTV-9" start="20251129054600 +0800" stop="20251129064700 +0800">
		<title lang="zh">全景自然2025-332</title>
	</programme>
	<programme channel="CCTV-9" start="20251129064700 +0800" stop="20251129074300 +0800">
		<title lang="zh">魅力万象2025-333</title>
	</programme>
	<programme channel="CCTV-9" start="20251129074300 +0800" stop="20251129075900 +0800">
		<title lang="zh">9视频2025-332</title>
	</programme>
	<programme channel="CCTV-9" start="20251129075900 +0800" stop="20251129093300 +0800">
		<title lang="zh">纪录影院2025-48</title>
	</programme>
	<programme channel="CCTV-9" start="20251129093300 +0800" stop="20251129103200 +0800">
		<title lang="zh">魅力万象2025-304</title>
	</programme>
	<programme channel="CCTV-9" start="20251129103200 +0800" stop="20251129113100 +0800">
		<title lang="zh">全景自然2025-304</title>
	</programme>
	<programme channel="CCTV-9" start="20251129113100 +0800" stop="20251129123200 +0800">
		<title lang="zh">魅力万象2025-305</title>
	</programme>
	<programme channel="CCTV-9" start="20251129123200 +0800" stop="20251129133100 +0800">
		<title lang="zh">全景自然2025-307</title>
	</programme>
	<programme channel="CCTV-9" start="20251129133100 +0800" stop="20251129143000 +0800">
		<title lang="zh">魅力万象2025-308</title>
	</programme>
	<programme channel="CCTV-9" start="20251129143000 +0800" stop="20251129153000 +0800">
		<title lang="zh">全景自然2025-308</title>
	</programme>
	<programme channel="CCTV-9" start="20251129153000 +0800" stop="20251129162900 +0800">
		<title lang="zh">魅力万象2025-309</title>
	</programme>
	<programme channel="CCTV-9" start="20251129162900 +0800" stop="20251129172800 +0800">
		<title lang="zh">全景自然2025-309</title>
	</programme>
	<programme channel="CCTV-9" start="20251129172800 +0800" stop="20251129182700 +0800">
		<title lang="zh">全景自然2025-333</title>
	</programme>
	<programme channel="CCTV-9" start="20251129182700 +0800" stop="20251129192700 +0800">
		<title lang="zh">魅力万象2025-334</title>
	</programme>
	<programme channel="CCTV-9" start="20251129192700 +0800" stop="20251129200000 +0800">
		<title lang="zh">活力·源2025-350</title>
	</programme>
	<programme channel="CCTV-9" start="20251129200000 +0800" stop="20251129210000 +0800">
		<title lang="zh">特别呈现2025-328</title>
	</programme>
	<programme channel="CCTV-9" start="20251129210000 +0800" stop="20251129220400 +0800">
		<title lang="zh">寰宇视野2025-333</title>
	</programme>
	<programme channel="CCTV-9" start="20251129220400 +0800" stop="20251129230600 +0800">
		<title lang="zh">故事中国2025-310</title>
	</programme>
	<programme channel="CCTV-9" start="20251129230600 +0800" stop="20251129232700 +0800">
		<title lang="zh">9视频2025-333</title>
	</programme>
	<programme channel="CCTV-9" start="20251129232700 +0800" stop="20251129235900 +0800">
		<title lang="zh">寰宇视野2025-333</title>
	</programme>
</tv>
